surecr/__init__.py
surecr/admm.py
surecr/divergence.py
surecr/prox_grad.py
surecr/prox_lib.py
surecr/solver.py
surecr/sure.py
surecr-0.1.2.dist-info/LICENSE
surecr-0.1.2.dist-info/METADATA
surecr-0.1.2.dist-info/WHEEL
surecr-0.1.2.dist-info/top_level.txt
surecr-0.1.2.dist-info/RECORD
