Metadata-Version: 2.1
Name: surecr
Version: 0.1.2
Summary: This package enables tractable evaluation of Stein's Unbiased Risk Estimate on convexly regularized estimators.
Home-page: https://github.com/cvxgrp/SURE-CR
Author: Parth Nobel
Author-email: ptnobel@stanford.edu
License: UNKNOWN
Platform: UNKNOWN
Classifier: Programming Language :: Python :: 3
Requires-Dist: cvxpy
Requires-Dist: cvxpylayers
Requires-Dist: numpy (>=1.17.5)
Requires-Dist: scipy
Requires-Dist: torch
Requires-Dist: torch-linops
